pydantic_llm_tester/.env.example
pydantic_llm_tester/__init__.py
pydantic_llm_tester/llm_tester.py
pydantic_llm_tester/bridge/README.md
pydantic_llm_tester/bridge/__init__.py
pydantic_llm_tester/bridge/analysis_report.py
pydantic_llm_tester/bridge/pyllm_bridge.py
pydantic_llm_tester/cli/__init__.py
pydantic_llm_tester/cli/interactive_ui.py
pydantic_llm_tester/cli/main.py
pydantic_llm_tester/cli/commands/__init__.py
pydantic_llm_tester/cli/commands/configure.py
pydantic_llm_tester/cli/commands/costs.py
pydantic_llm_tester/cli/commands/interactive.py
pydantic_llm_tester/cli/commands/models.py
pydantic_llm_tester/cli/commands/paths.py
pydantic_llm_tester/cli/commands/prices.py
pydantic_llm_tester/cli/commands/providers.py
pydantic_llm_tester/cli/commands/recommend.py
pydantic_llm_tester/cli/commands/run.py
pydantic_llm_tester/cli/commands/scaffold.py
pydantic_llm_tester/cli/commands/schemas.py
pydantic_llm_tester/cli/core/__init__.py
pydantic_llm_tester/cli/core/config_logic.py
pydantic_llm_tester/cli/core/cost_update_logic.py
pydantic_llm_tester/cli/core/llm_model_logic.py
pydantic_llm_tester/cli/core/model_config_logic.py
pydantic_llm_tester/cli/core/price_query_logic.py
pydantic_llm_tester/cli/core/provider_logic.py
pydantic_llm_tester/cli/core/recommend_logic.py
pydantic_llm_tester/cli/core/scaffold_logic.py
pydantic_llm_tester/cli/core/schema_logic.py
pydantic_llm_tester/cli/core/test_runner_logic.py
pydantic_llm_tester/cli/templates/__init__.py
pydantic_llm_tester/cli/templates/model_init.py.tmpl
pydantic_llm_tester/cli/templates/model_model.py.tmpl
pydantic_llm_tester/cli/templates/model_test_expected.json.tmpl
pydantic_llm_tester/cli/templates/model_test_prompt.txt.tmpl
pydantic_llm_tester/cli/templates/model_test_source.txt.tmpl
pydantic_llm_tester/cli/templates/model_tests_init.py.tmpl
pydantic_llm_tester/cli/templates/provider_config.json.tmpl
pydantic_llm_tester/cli/templates/provider_init.py.tmpl
pydantic_llm_tester/cli/templates/provider_provider.py.tmpl
pydantic_llm_tester-0.1.20.dist-info/licenses/LICENSE
pydantic_llm_tester-0.1.20.dist-info/METADATA
pydantic_llm_tester-0.1.20.dist-info/WHEEL
pydantic_llm_tester-0.1.20.dist-info/entry_points.txt
pydantic_llm_tester-0.1.20.dist-info/top_level.txt
pydantic_llm_tester-0.1.20.dist-info/RECORD
