Metadata-Version: 2.4
Name: pydantic-llm-tester
Version: 0.1.20
Summary: A framework for testing LLM performance using pydanticAI
Author-email: Timo Railo <firstname@east.fi>
License: MIT License
Classifier: Development Status :: 3 - Alpha
Classifier: Intended Audience :: Developers
Classifier: License :: OSI Approved :: MIT License
Classifier: Programming Language :: Python :: 3
Classifier: Programming Language :: Python :: 3.8
Classifier: Programming Language :: Python :: 3.9
Classifier: Programming Language :: Python :: 3.10
Classifier: Programming Language :: Python :: 3.11
Requires-Python: >=3.9
License-File: LICENSE
Requires-Dist: pydantic>=2.10.6
Requires-Dist: openai>=1.0.0
Requires-Dist: anthropic>=0.5.0
Requires-Dist: mistralai>=1.6.0
Requires-Dist: google-cloud-aiplatform
Requires-Dist: python-dotenv>=1.0.1
Requires-Dist: typer>=0.15.2
Requires-Dist: pydantic-ai>=0.0.44
Requires-Dist: rapidfuzz>=3.12.2
Requires-Dist: requests>=2.32.3
Requires-Dist: google-genai
Dynamic: license-file
